{
	"cmcYkshsZH3VERwsRbB5L7": {
		"firstPlayed": "2024-08-30T11:53:55.825Z",
		"lastPlayed": "2024-08-30T11:59:58.556Z",
		"totalPlayed": 0
	},
	"oG8AhzkkbrooG1q9t61nEY": {
		"firstPlayed": "2024-08-30T11:54:56.692Z"
	},
	"1mBLrGNHmFe9rP2QJ4zq1A": {
		"firstPlayed": "2024-08-30T12:51:50.517Z",
		"lastPlayed": "2024-08-30T14:25:18.439Z",
		"totalPlayed": 71
	},
	"tAhV7r6wRURYCSkbFcAjA9": {
		"firstPlayed": "2024-08-30T15:24:31.342Z",
		"lastPlayed": "2024-08-30T15:45:31.683Z",
		"totalPlayed": 1
	},
	"1hC5FRWgaXw8sJYkuSGCB1": {
		"firstPlayed": "2024-08-30T15:45:10.617Z"
	},
	"9uzexp9hrgq8LHy2GibzPa": {
		"firstPlayed": "2024-08-30T15:46:32.161Z"
	}
}